qpay_client/__init__.py
qpay_client/py.typed
qpay_client/v2/__init__.py
qpay_client/v2/auth.py
qpay_client/v2/client.py
qpay_client/v2/enums.py
qpay_client/v2/error.py
qpay_client/v2/schemas.py
qpay_client/v2/settings.py
qpay_client/v2/sync_client.py
qpay_client/v2/types.py
qpay_client/v2/utils.py
qpay_client-1.0.0.dist-info/WHEEL
qpay_client-1.0.0.dist-info/METADATA
qpay_client-1.0.0.dist-info/RECORD
