Metadata-Version: 2.3
Name: qpay-client
Version: 1.0.0
Summary: QPay Integration made easy (async & sync, typed schemas, auto token refresh)
Keywords: qpay,payment,qpay v2,mongolian payment,mongolia,httpx,pydantic,asyncio
Author: Amraa1
Author-email: Amraa1 <amarsanaaganbaatar0409@gmail.com>
License: MIT License
Classifier: Intended Audience :: Developers
Classifier: Topic :: Software Development :: Libraries :: Python Modules
Classifier: License :: OSI Approved :: MIT License
Classifier: Programming Language :: Python :: 3
Classifier: Programming Language :: Python :: 3.9
Classifier: Programming Language :: Python :: 3.10
Classifier: Programming Language :: Python :: 3.11
Classifier: Programming Language :: Python :: 3.12
Classifier: Programming Language :: Python :: 3.13
Classifier: Programming Language :: Python :: 3.14
Classifier: Typing :: Typed
Requires-Dist: httpx>=0.28.1
Requires-Dist: pydantic>=2.10.0
Requires-Dist: pydantic-settings>=2.11.0
Requires-Dist: sphinx>=7.4.7 ; extra == 'docs'
Requires-Dist: sphinx-rtd-theme>=3.0.2 ; extra == 'docs'
Requires-Python: >=3.9
Project-URL: Documentation, https://qpay-client.readthedocs.io/mn/latest/
Project-URL: Homepage, https://pypi.org/project/qpay-client/
Project-URL: Issues, https://github.com/Amraa1/qpay_client/issues
Project-URL: Source, https://github.com/Amraa1/qpay_client
Provides-Extra: docs
